smallPackage/__init__.py
smallPackage/adder.py
smallPackage/module1.py
smallPackage-0.1.0.dist-info/LICENSE
smallPackage-0.1.0.dist-info/METADATA
smallPackage-0.1.0.dist-info/WHEEL
smallPackage-0.1.0.dist-info/top_level.txt
smallPackage-0.1.0.dist-info/RECORD
