Metadata-Version: 2.1
Name: smallPackage
Version: 0.1.0
Summary: Describe your package in one sentence
Home-page: https://github.com/you/your_package
Author: Sam
Author-email: samkoshythomas@gmail.com
License: Apache License 2.0
Platform: UNKNOWN
License-File: LICENSE
Requires-Dist: numpy
Requires-Dist: pandas
